[
  {
    "id": "demo_001",
    "title": "课堂提问反馈不足",
    "cat": "教学反思",
    "tags": [
      "课堂互动",
      "三年级"
    ],
    "sit": "今天数学课上提问时，只有少数同学举手。发现大部分学生其实没有理解题目，但不敢说。",
    "ref": "我应该给学生更多思考时间，而不是急着要点名回答。提问的方式也需要调整。",
    "imp": "下次采用\"思考-配对-分享\"模式：先给30秒独立思考，再同桌讨论，最后全班分享。",
    "fol": "已经在另一班试了一次，举手人数明显增加。",
    "date": "2026-06-10T08:30:00.000Z"
  },
  {
    "id": "demo_002",
    "title": "作业布置量过大",
    "cat": "教学反思",
    "tags": [
      "作业"
    ],
    "sit": "周一检查周末作业，发现超过一半学生没完成。询问后发现是作业量确实偏多。",
    "ref": "作业不在量多而在质精。布置前应该自己先做一遍预估时间。",
    "imp": "控制每次作业在20分钟内完成。布置分层作业，基础题+选做题。",
    "fol": "",
    "date": "2026-06-08T14:00:00.000Z"
  },
  {
    "id": "demo_003",
    "title": "班级纪律需要改善",
    "cat": "班级管理",
    "tags": [
      "纪律",
      "课堂管理"
    ],
    "sit": "下午第二节课，后排几个同学一直在说话，提醒两次后依然没改。",
    "ref": "单纯批评效果不好，需要建立正向激励机制。",
    "imp": "设计\"课堂积分制\"：认真听讲+回答问题可获积分，每周兑换小奖励。",
    "fol": "开始试行，第一周效果良好。",
    "date": "2026-06-05T15:20:00.000Z"
  },
  {
    "id": "demo_004",
    "title": "学生主动帮助同学",
    "cat": "个人成长",
    "tags": [
      "学生互动",
      "正向行为"
    ],
    "sit": "课间看到小张主动给同桌讲解数学题，讲得非常耐心。",
    "ref": "学生的善意需要被看见和鼓励。这种互助精神应该在班级中推广。",
    "imp": "在班会课上专门表扬了这种行为，设立了\"互助小天使\"称号。",
    "fol": "之后陆续有更多的同学开始互帮互助。",
    "date": "2026-06-03T10:15:00.000Z"
  }
]